<package-actions>
    <!-- Validace pravidel ZP2015 -->
    <package-action filename="ZP2015_FUND_VALIDATION.yaml" >
        <action-recommendeds>
            <action-recommended output-type="STARSI_POMUCKA_1958" />
            <action-recommended output-type="ZP2015_MANIP_SEZNAM" />
            <action-recommended output-type="ZP2015_INVENTAR" />
        </action-recommendeds>
    </package-action>
    <package-action filename="ZP2015_GENERATOR_SERIAL_NUMBER.yaml" >
        <action-recommendeds>
            <action-recommended output-type="STARSI_POMUCKA_1958" />
            <action-recommended output-type="ZP2015_MANIP_SEZNAM" />
            <action-recommended output-type="ZP2015_INVENTAR" />
            <action-recommended output-type="ZP2015_STITKY" />
        </action-recommendeds>
    </package-action>
    <package-action filename="ZNEPLATNENI_INV_CISLA.yaml" >
    </package-action>
    <package-action filename="GENEROVANI_INV_CISLA.yaml" >
    </package-action>
    <package-action filename="ZP2015_GENERATOR_UNIT_ID.yaml" >
        <action-recommendeds>
            <action-recommended output-type="ZP2015_INVENTAR" />
            <action-recommended output-type="ZP2015_STITKY" />
        </action-recommendeds>
    </package-action>
    <package-action filename="ZMRAZENI_REF_OZN.yaml" />
    <!-- Agregace uvodu -->
    <package-action filename="ZP2015_INTRO.yaml">
        <action-item-types>
            <action-item-type item-type="ZP2015_UNIT_SOURCE" />
            <action-item-type item-type="ZP2015_UNIT_HIST" />
            <action-item-type item-type="ZP2015_UNIT_ARR" />
            <action-item-type item-type="ZP2015_UNIT_CONTENT" />
            <action-item-type item-type="ZP2015_FUTURE_UNITS" />
            <action-item-type item-type="ZP2015_RELATED_UNITS" />
            <action-item-type item-type="ZP2015_UNIT_CURRENT_STATUS" />
            <action-item-type item-type="ZP2015_ARRANGE_RULES" />
            <action-item-type item-type="ZP2015_DESCRIPTION_DATE" />
            <action-item-type item-type="ZP2015_DATE_RANGE" />
            <action-item-type item-type="ZP2015_ARRANGER" />
            <action-item-type item-type="ZP2015_ARRANGEMENT_INFO" />
            <action-item-type item-type="ZP2015_LANGUAGE" />
            <action-item-type item-type="ZP2015_UNIT_COUNT_SUM" />
            <action-item-type item-type="ZP2015_UNIT_COUNT_TABLE" />
            <action-item-type item-type="ZP2015_ORIGINATOR_SIMPLE" />
            <action-item-type item-type="ZP2015_ATTACHMENT" />
            <action-item-type item-type="ZP2015_UNIT_DAMAGE_TYPE" />
        </action-item-types>
        <action-recommendeds>
            <action-recommended output-type="STARSI_POMUCKA_1958" />
            <action-recommended output-type="ZP2015_MANIP_SEZNAM" />
            <action-recommended output-type="ZP2015_INVENTAR" />
        </action-recommendeds>
    </package-action>
    <!-- Generator testovacich dat -->
    <package-action filename="ZP2015_TEST_DATA_GENERATOR.yaml">
    </package-action>
    <package-action filename="PERZISTENTNI_RAZENI.yaml" />
    <!-- Vypocet a vizualizace EJ -->
    <package-action filename="ZP2015_INTRO_VYPOCET_EJ.yaml"/>
    <package-action filename="GENEROVANI_PORADI_ULOZENI.yaml" />
    <!-- Generování ukládacích jednotek -->
    <package-action filename="GENEROVANI_UKL_JEDNOTEK.yaml" />
    <package-action filename="MAZANI_UKL_JEDNOTEK.yaml" />
</package-actions>
