<?xml version="1.0" encoding="UTF-8"?>
<databaseChangeLog
        xmlns="http://www.liquibase.org/xml/ns/dbchangelog"
        xmlns:xsi="http://www.w3.org/2001/XMLSchema-instance"
        xsi:schemaLocation="http://www.liquibase.org/xml/ns/dbchangelog http://www.liquibase.org/xml/ns/dbchangelog/dbchangelog-3.4.xsd">

    <changeSet id="61" author="vanek">
        <createTable tableName="ui_party_group">
            <column name="party_group_id" type="int">
                <constraints primaryKey="true"/>
            </column>
            <column name="party_type_id" type="int">
                <constraints nullable="true" foreignKeyName="fk_party_type" referencedTableName="par_party_type" referencedColumnNames="party_type_id"/>
            </column>
            <column name="code" type="nvarchar(50)">
                <constraints nullable="false" unique="true"/>
            </column>
            <column name="name" type="nvarchar(50)">
                <constraints nullable="false"/>
            </column>
            <column name="view_order" type="int">
                <constraints nullable="false"/>
            </column>
            <column name="type" type="char(10)">
                <constraints nullable="false"/>
            </column>
            <column name="content_definition" type="${type.text}">
                <constraints nullable="false"/>
            </column>
        </createTable>
    </changeSet>
</databaseChangeLog>
